jupyterlab_hide_cells/__init__.py
jupyterlab_hide_cells/_version.py
jupyterlab_hide_cells/labextension/package.json
jupyterlab_hide_cells/labextension/static/48.162a9391112dedcff9ce.js
jupyterlab_hide_cells/labextension/static/728.f11e1442be17d933055a.js
jupyterlab_hide_cells/labextension/static/remoteEntry.19bf105e5f6711ef0a80.js
jupyterlab_hide_cells/labextension/static/style.js
jupyterlab_hide_cells/labextension/static/third-party-licenses.json
jupyterlab_hide_cells-3.0.1.data/data/share/jupyter/labextensions/jupyterlab-hide-cells/package.json
jupyterlab_hide_cells-3.0.1.data/data/share/jupyter/labextensions/jupyterlab-hide-cells/static/48.162a9391112dedcff9ce.js
jupyterlab_hide_cells-3.0.1.data/data/share/jupyter/labextensions/jupyterlab-hide-cells/static/728.f11e1442be17d933055a.js
jupyterlab_hide_cells-3.0.1.data/data/share/jupyter/labextensions/jupyterlab-hide-cells/static/remoteEntry.19bf105e5f6711ef0a80.js
jupyterlab_hide_cells-3.0.1.data/data/share/jupyter/labextensions/jupyterlab-hide-cells/static/style.js
jupyterlab_hide_cells-3.0.1.data/data/share/jupyter/labextensions/jupyterlab-hide-cells/static/third-party-licenses.json
jupyterlab_hide_cells-3.0.1.data/data/share/jupyter/labextensions/jupyterlab-hide-cells/install.json
jupyterlab_hide_cells-3.0.1.dist-info/METADATA
jupyterlab_hide_cells-3.0.1.dist-info/WHEEL
jupyterlab_hide_cells-3.0.1.dist-info/licenses/LICENSE
jupyterlab_hide_cells-3.0.1.dist-info/RECORD
