Metadata-Version: 2.3
Name: jupyterlab_hide_cells
Version: 3.0.1
Dynamic: Keywords
Summary: A JupyterLab extension.
Project-URL: Homepage, https://git.rwth-aachen.de/learntech-lufgi9/public/jupyterlab-hide-cells.git
Project-URL: Bug Tracker, https://git.rwth-aachen.de/learntech-lufgi9/public/jupyterlab-hide-cells.git/issues
Project-URL: Repository, https://git.rwth-aachen.de/learntech-lufgi9/public/jupyterlab-hide-cells.git.git
Author-email: Annabell Brocker <a.brocker@cs.rwth-aachen.de>
License: MIT License
License-File: LICENSE
Classifier: Framework :: Jupyter
Classifier: Framework :: Jupyter :: JupyterLab
Classifier: Framework :: Jupyter :: JupyterLab :: 4
Classifier: Framework :: Jupyter :: JupyterLab :: Extensions
Classifier: Framework :: Jupyter :: JupyterLab :: Extensions :: Prebuilt
Classifier: License :: OSI Approved :: BSD License
Classifier: Programming Language :: Python
Classifier: Programming Language :: Python :: 3
Classifier: Programming Language :: Python :: 3.8
Classifier: Programming Language :: Python :: 3.9
Classifier: Programming Language :: Python :: 3.10
Classifier: Programming Language :: Python :: 3.11
Classifier: Programming Language :: Python :: 3.12
Requires-Python: >=3.8
